{
  "name": "Profile",
  "fields": [
    {
      "fieldName": "userId",
      "fieldType": "Long",
      "fieldValidateRules": ["required"]
    },
    {
      "fieldName": "login",
      "fieldType": "String",
      "fieldValidateRules": ["required", "maxlength"],
      "fieldValidateRulesMaxlength": "100"
    },
    {
      "fieldName": "phone",
      "fieldType": "String",
      "fieldValidateRules": ["required", "minlength", "maxlength"],
      "fieldValidateRulesMinlength": "8",
      "fieldValidateRulesMaxlength": "15"
    },
    {
      "fieldName": "email",
      "fieldType": "String"
    },
    {
      "fieldName": "firstName",
      "fieldType": "String",
      "fieldValidateRules": ["required"]
    },
    {
      "fieldName": "middleName",
      "fieldType": "String"
    },
    {
      "fieldName": "lastName",
      "fieldType": "String",
      "fieldValidateRules": ["required"]
    },
    {
      "fieldName": "optActivationKey",
      "fieldType": "String"
    },
    {
      "fieldName": "activationKey",
      "fieldType": "String"
    },
    {
      "fieldName": "alias",
      "fieldType": "String"
    },
    {
      "fieldName": "emailNotifications",
      "fieldType": "Boolean"
    },
    {
      "fieldName": "smsNotifications",
      "fieldType": "Boolean"
    },
    {
      "fieldName": "photo",
      "fieldType": "byte[]",
      "fieldTypeBlobContent": "image"
    },
    {
      "fieldName": "lang",
      "fieldType": "String",
      "javadoc": "Used for i18n on the platform",
      "fieldValidateRules": ["required"]
    }
  ],
  "relationships": [],
  "changelogDate": "20200926132924",
  "entityTableName": "profile",
  "dto": "mapstruct",
  "pagination": "pagination",
  "service": "serviceImpl",
  "jpaMetamodelFiltering": true,
  "fluentMethods": true,
  "readOnly": false,
  "embedded": false,
  "clientRootFolder": "coreservice",
  "applications": "*",
  "microserviceName": "coreservice"
}
